h_transport_materials/__init__.py
h_transport_materials/_version.py
h_transport_materials/conversion.py
h_transport_materials/helpers.py
h_transport_materials/material.py
h_transport_materials/plotting.py
h_transport_materials/properties_group.py
h_transport_materials/property.py
h_transport_materials/references.bib
h_transport_materials/property_database/__init__.py
h_transport_materials/property_database/beryllium.py
h_transport_materials/property_database/carbon.py
h_transport_materials/property_database/chromium.py
h_transport_materials/property_database/gold.py
h_transport_materials/property_database/hastelloy_n.py
h_transport_materials/property_database/hastelloy_x.py
h_transport_materials/property_database/incoloy_800.py
h_transport_materials/property_database/inconel_600.py
h_transport_materials/property_database/inconel_625.py
h_transport_materials/property_database/inconel_750.py
h_transport_materials/property_database/iron.py
h_transport_materials/property_database/molybdenum.py
h_transport_materials/property_database/nickel.py
h_transport_materials/property_database/nimonic_80A.py
h_transport_materials/property_database/niobium.py
h_transport_materials/property_database/palladium.py
h_transport_materials/property_database/palladium_copper.py
h_transport_materials/property_database/rafm_steel.py
h_transport_materials/property_database/series_300_steel.py
h_transport_materials/property_database/sic.py
h_transport_materials/property_database/silver.py
h_transport_materials/property_database/tantalum.py
h_transport_materials/property_database/titanium.py
h_transport_materials/property_database/tzm.py
h_transport_materials/property_database/vanadium.py
h_transport_materials/property_database/vanadium_alloy.py
h_transport_materials/property_database/yttrium.py
h_transport_materials/property_database/FeCrAl/__init__.py
h_transport_materials/property_database/FeCrAl/apmt/Hu_APMT_2015.csv
h_transport_materials/property_database/FeCrAl/apmt/__init__.py
h_transport_materials-0.18.dist-info/licenses/LICENSE
h_transport_materials-0.18.dist-info/METADATA
h_transport_materials-0.18.dist-info/WHEEL
h_transport_materials-0.18.dist-info/top_level.txt
h_transport_materials-0.18.dist-info/RECORD
