Metadata-Version: 2.4
Name: h_transport_materials
Version: 0.18
Summary: Handle H transport properties
Home-page: https://github.com/RemDelaporteMathurin/h_transport_materials
Author: Remi Delaporte-Mathurin
Author-email: rdelaportemathurin@gmail.com
License: MIT
Project-URL: Source, https://github.com/RemDelaporteMathurin/h_transport_materials
Project-URL: Tracker, https://github.com/RemDelaporteMathurin/h_transport_materials/issues
Classifier: Natural Language :: English
Classifier: Topic :: Scientific/Engineering
Classifier: Programming Language :: Python :: 3
Classifier: Programming Language :: Python :: 3.6
Classifier: Programming Language :: Python :: 3.7
Classifier: Programming Language :: Python :: 3.8
Classifier: Programming Language :: Python :: 3.9
Classifier: Programming Language :: Python :: 3.10
Classifier: License :: OSI Approved :: MIT License
Classifier: Operating System :: OS Independent
Requires-Python: >=3.6
License-File: LICENSE
Requires-Dist: numpy>=1.9
Requires-Dist: matplotlib>=3.2.2
Requires-Dist: pybtex==0.24.0
Requires-Dist: crossrefapi==1.5.0
Requires-Dist: scipy>=1.8
Requires-Dist: pint
Provides-Extra: tests
Requires-Dist: pytest-cov==4.0.0; extra == "tests"
Provides-Extra: plotly
Requires-Dist: plotly; extra == "plotly"
Dynamic: license-file
